adafruit_ble_adafruit/__init__.py
adafruit_ble_adafruit/accelerometer_service.py
adafruit_ble_adafruit/adafruit_service.py
adafruit_ble_adafruit/addressable_pixel_service.py
adafruit_ble_adafruit/barometric_pressure_service.py
adafruit_ble_adafruit/button_service.py
adafruit_ble_adafruit/color_sensor_service.py
adafruit_ble_adafruit/gesture_service.py
adafruit_ble_adafruit/gyroscope_service.py
adafruit_ble_adafruit/humidity_service.py
adafruit_ble_adafruit/light_sensor_service.py
adafruit_ble_adafruit/magnetometer_service.py
adafruit_ble_adafruit/microphone_service.py
adafruit_ble_adafruit/proximity_service.py
adafruit_ble_adafruit/quaternion_service.py
adafruit_ble_adafruit/temperature_service.py
adafruit_ble_adafruit/tone_service.py
adafruit_circuitpython_ble_adafruit-1.4.14.dist-info/licenses/LICENSE
adafruit_circuitpython_ble_adafruit-1.4.14.dist-info/METADATA
adafruit_circuitpython_ble_adafruit-1.4.14.dist-info/WHEEL
adafruit_circuitpython_ble_adafruit-1.4.14.dist-info/top_level.txt
adafruit_circuitpython_ble_adafruit-1.4.14.dist-info/RECORD
