Metadata-Version: 2.4
Name: adafruit-circuitpython-ble-adafruit
Version: 1.4.14
Summary: Access to sensors and hardware on or connected to BLE-capable boards
Author-email: Adafruit Industries <circuitpython@adafruit.com>
License: MIT
Project-URL: Homepage, https://github.com/adafruit/Adafruit_CircuitPython_BLE_Adafruit
Keywords: adafruit,blinka,circuitpython,micropython,circuitplayground,bluefruit,CLUE,ble
Classifier: Intended Audience :: Developers
Classifier: Topic :: Software Development :: Libraries
Classifier: Topic :: Software Development :: Embedded Systems
Classifier: Topic :: System :: Hardware
Classifier: License :: OSI Approved :: MIT License
Classifier: Programming Language :: Python :: 3
License-File: LICENSE
Requires-Dist: Adafruit-Blinka
Requires-Dist: adafruit-circuitpython-ble
Provides-Extra: optional
Dynamic: license-file
